<?xml version="1.0"?>
<opencv_storage>
<Settings>
  <!-- Number of inner corners per a item row and column. (square, circle) -->
  <BoardSize_Width>8</BoardSize_Width>
  <BoardSize_Height>6</BoardSize_Height>
  
  <!-- The size of a square in some user defined metric system (pixel, millimeter)-->
  <Square_Size>115</Square_Size>
  
  <!-- The type of input used for camera calibration. One of: CHESSBOARD CIRCLES_GRID ASYMMETRIC_CIRCLES_GRID -->
  <Calibrate_Pattern>"CHESSBOARD"</Calibrate_Pattern>
  
  <!--  If true (non-zero) we flip the input images around the horizontal axis.-->
  <Input_FlipAroundHorizontalAxis>0</Input_FlipAroundHorizontalAxis>
  
  <!-- Time delay between frames in case of camera. -->
  <Input_Delay>100</Input_Delay>	
  
  <!-- How many frames to use, for calibration. -->
  <Calibrate_NrOfFrameToUse>25</Calibrate_NrOfFrameToUse>
  <!-- Consider only fy as a free parameter, the ratio fx/fy stays the same as in the input cameraMatrix. 
	   Use or not setting. 0 - False Non-Zero - True-->
  <Calibrate_FixAspectRatio> 1 </Calibrate_FixAspectRatio>
  <!-- If true (non-zero) tangential distortion coefficients  are set to zeros and stay zero.-->
  <Calibrate_AssumeZeroTangentialDistortion>1</Calibrate_AssumeZeroTangentialDistortion>
  <!-- If true (non-zero) the principal point is not changed during the global optimization.-->
  <Calibrate_FixPrincipalPointAtTheCenter> 1 </Calibrate_FixPrincipalPointAtTheCenter>
  
 
</Settings>
</opencv_storage>
